{
  "_id": "edc9086ecdd546eb",
  "name": "Fiend CR 0-1 Harvest Table",
  "description": "<p>Generic harvest table for fiends of CR 0-1.</p>",
  "formula": "1d20",
  "replacement": true,
  "displayRoll": true,
  "results": [
    {
      "_id": "2e2cd9fb4716e016",
      "text": "Infernal Ash",
      "type": "text",
      "range": [
        1,
        3
      ],
      "weight": 1,
      "drawn": false,
      "flags": {
        "ultimate-harvester": {
          "rarity": "common",
          "itemUuid": "Compendium.ultimate-harvester.harvest-items.d1607b57a65b4fe6",
          "quantity": "1d4",
          "category": "component"
        }
      },
      "_key": "!tables.results!edc9086ecdd546eb.2e2cd9fb4716e016",
      "description": "Infernal Ash",
      "name": "",
      "img": null,
      "_stats": {
        "compendiumSource": null,
        "duplicateSource": null,
        "exportSource": null
      }
    },
    {
      "_id": "2417a601e9040200",
      "text": "Demon Ichor",
      "type": "text",
      "range": [
        1,
        3
      ],
      "weight": 1,
      "drawn": false,
      "flags": {
        "ultimate-harvester": {
          "rarity": "common",
          "itemUuid": "Compendium.ultimate-harvester.harvest-items.13304f7dbf262f5a",
          "quantity": "1",
          "category": "component"
        }
      },
      "_key": "!tables.results!edc9086ecdd546eb.2417a601e9040200",
      "description": "Demon Ichor",
      "name": "",
      "img": null,
      "_stats": {
        "compendiumSource": null,
        "duplicateSource": null,
        "exportSource": null
      }
    },
    {
      "_id": "120cb145f5521f15",
      "text": "Devil Horn",
      "type": "text",
      "range": [
        1,
        3
      ],
      "weight": 1,
      "drawn": false,
      "flags": {
        "ultimate-harvester": {
          "rarity": "uncommon",
          "itemUuid": "Compendium.ultimate-harvester.harvest-items.f892e958e343af49",
          "quantity": "1",
          "category": "material"
        }
      },
      "_key": "!tables.results!edc9086ecdd546eb.120cb145f5521f15",
      "description": "Devil Horn",
      "name": "",
      "img": null,
      "_stats": {
        "compendiumSource": null,
        "duplicateSource": null,
        "exportSource": null
      }
    },
    {
      "_id": "4ed1b8b7901ad25d",
      "text": "Fiendish Hide",
      "type": "text",
      "range": [
        1,
        3
      ],
      "weight": 1,
      "drawn": false,
      "flags": {
        "ultimate-harvester": {
          "rarity": "rare",
          "itemUuid": "Compendium.ultimate-harvester.harvest-items.78ce2cc2921a204b",
          "quantity": "1",
          "category": "material"
        }
      },
      "_key": "!tables.results!edc9086ecdd546eb.4ed1b8b7901ad25d",
      "description": "Fiendish Hide",
      "name": "",
      "img": null,
      "_stats": {
        "compendiumSource": null,
        "duplicateSource": null,
        "exportSource": null
      }
    }
  ],
  "flags": {
    "ultimate-harvester": {
      "critFailEffect": "A burst of infernal energy scorches your hands; take 1d6 fire damage.",
      "fumbleEffect": "The infernal ash irritates your lungs; you cough for 1 minute and have disadvantage on Stealth checks.",
      "critSuccessQuantity": "1"
    }
  },
  "_key": "!tables!edc9086ecdd546eb",
  "img": "icons/svg/d20-grey.svg",
  "folder": null,
  "sort": 0,
  "ownership": {
    "default": 0
  },
  "_stats": {
    "compendiumSource": null,
    "duplicateSource": null,
    "exportSource": null
  }
}