{
  "_id": "2dbe44e15714eddf",
  "name": "Giant Heart",
  "type": "loot",
  "img": "icons/commodities/biological/organ-heart-pink.webp",
  "system": {
    "description": {
      "value": "<p><em>A massive heart the size of a barrel; valued by potion-brewers.</em></p><hr/><section style=\"border-left: 3px solid #5E9B6D; padding-left: 8px; margin-top: 6px;\"><p><strong>Crafting Use:</strong> Strength reagent — brewed into greater giant-strength potions and titan elixirs.</p><p><strong>Value when used in crafting:</strong> 30 gp</p></section>"
    },
    "weight": {
      "value": 8,
      "units": "lb"
    },
    "price": {
      "value": 6,
      "denomination": "gp"
    },
    "rarity": "rare",
    "quantity": 1
  },
  "flags": {
    "ultimate-harvester": {
      "category": "component"
    }
  },
  "_key": "!items!2dbe44e15714eddf",
  "folder": null,
  "sort": 0,
  "ownership": {
    "default": 0
  },
  "_stats": {
    "compendiumSource": null,
    "duplicateSource": null,
    "exportSource": null
  }
}
